<?xml version="1.0" encoding="us-ascii"?>
<Pos xmlns:xsi="http://www.w3.org/2001/XMLSchema-instance" xmlns:xsd="http://www.w3.org/2001/XMLSchema">
  <Positions>
    <position>
      <x>-39.4064941</x>
      <y>0.8099128</y>
      <z>10</z>
    </position>
    <position>
      <x>-39.4064941</x>
      <y>3.00991273</y>
      <z>10</z>
    </position>
    <position>
      <x>-39.4064941</x>
      <y>4.709912</y>
      <z>10</z>
    </position>
    <position>
      <x>-38.6564865</x>
      <y>5.91756248</y>
      <z>10</z>
    </position>
    <position>
      <x>-37.90648</x>
      <y>5.617563</y>
      <z>10</z>
    </position>
    <position>
      <x>-37.15647</x>
      <y>4.81756353</y>
      <z>10</z>
    </position>
    <position>
      <x>-36.4064636</x>
      <y>3.5175643</y>
      <z>10</z>
    </position>
    <position>
      <x>-36.2564621</x>
      <y>5.71756458</y>
      <z>10</z>
    </position>
    <position>
      <x>-36.2564621</x>
      <y>7.417564</y>
      <z>10</z>
    </position>
    <position>
      <x>-35.5064545</x>
      <y>8.617563</y>
      <z>10</z>
    </position>
    <position>
      <x>-34.7564468</x>
      <y>9.317564</y>
      <z>10</z>
    </position>
    <position>
      <x>-34.00644</x>
      <y>9.517563</y>
      <z>10</z>
    </position>
    <position>
      <x>-33.25643</x>
      <y>9.217562</y>
      <z>10</z>
    </position>
    <position>
      <x>-33.10643</x>
      <y>8.417562</y>
      <z>10</z>
    </position>
    <position>
      <x>-33.10643</x>
      <y>7.11756039</y>
      <z>10</z>
    </position>
    <position>
      <x>-33.8564377</x>
      <y>5.31755972</y>
      <z>10</z>
    </position>
    <position>
      <x>-34.6064453</x>
      <y>3.017559</y>
      <z>10</z>
    </position>
    <position>
      <x>-33.8564377</x>
      <y>2.564487</y>
      <z>10</z>
    </position>
    <position>
      <x>-33.10643</x>
      <y>2.564487</y>
      <z>10</z>
    </position>
    <position>
      <x>-32.95643</x>
      <y>4.76448727</y>
      <z>10</z>
    </position>
    <position>
      <x>-32.95643</x>
      <y>6.4644866</y>
      <z>10</z>
    </position>
    <position>
      <x>-33.10643</x>
      <y>8.664486</y>
      <z>10</z>
    </position>
    <position>
      <x>-33.10643</x>
      <y>10.3644857</y>
      <z>10</z>
    </position>
    <position>
      <x>-32.3564224</x>
      <y>11.5644855</y>
      <z>10</z>
    </position>
    <position>
      <x>-31.60642</x>
      <y>12.2644863</y>
      <z>10</z>
    </position>
    <position>
      <x>-31.45642</x>
      <y>12.4644852</y>
      <z>10</z>
    </position>
    <position>
      <x>-31.45642</x>
      <y>12.164484</y>
      <z>10</z>
    </position>
    <position>
      <x>-30.7064228</x>
      <y>11.3644838</y>
      <z>10</z>
    </position>
    <position>
      <x>-29.9564247</x>
      <y>10.0644836</y>
      <z>10</z>
    </position>
    <position>
      <x>-29.8064251</x>
      <y>8.264483</y>
      <z>10</z>
    </position>
    <position>
      <x>-29.8064251</x>
      <y>5.96448326</y>
      <z>10</z>
    </position>
    <position>
      <x>-29.8064251</x>
      <y>3.164483</y>
      <z>10</z>
    </position>
    <position>
      <x>-29.8064251</x>
      <y>2.564487</y>
      <z>10</z>
    </position>
    <position>
      <x>-29.8064251</x>
      <y>4.76448727</y>
      <z>10</z>
    </position>
    <position>
      <x>-29.8064251</x>
      <y>6.4644866</y>
      <z>10</z>
    </position>
    <position>
      <x>-29.056427</x>
      <y>7.66448545</y>
      <z>10</z>
    </position>
    <position>
      <x>-28.3064289</x>
      <y>8.364485</y>
      <z>10</z>
    </position>
    <position>
      <x>-27.55643</x>
      <y>8.564484</y>
      <z>10</z>
    </position>
    <position>
      <x>-26.8064327</x>
      <y>8.2644825</y>
      <z>10</z>
    </position>
    <position>
      <x>-26.6564331</x>
      <y>10.4644814</y>
      <z>10</z>
    </position>
    <position>
      <x>-26.6564331</x>
      <y>12.1644812</y>
      <z>10</z>
    </position>
    <position>
      <x>-25.906435</x>
      <y>13.364481</y>
      <z>10</z>
    </position>
    <position>
      <x>-25.1564369</x>
      <y>14.0644817</y>
      <z>10</z>
    </position>
    <position>
      <x>-24.4064388</x>
      <y>14.2644806</y>
      <z>10</z>
    </position>
    <position>
      <x>-23.65644</x>
      <y>13.9644794</y>
      <z>10</z>
    </position>
    <position>
      <x>-22.9064426</x>
      <y>13.1644793</y>
      <z>10</z>
    </position>
    <position>
      <x>-22.1564445</x>
      <y>11.8644791</y>
      <z>10</z>
    </position>
    <position>
      <x>-21.4064465</x>
      <y>10.0644789</y>
      <z>10</z>
    </position>
    <position>
      <x>-20.6564484</x>
      <y>7.76447773</y>
      <z>10</z>
    </position>
    <position>
      <x>-20.5064487</x>
      <y>5.78808451</y>
      <z>10</z>
    </position>
    <position>
      <x>-20.5064487</x>
      <y>5.78808451</y>
      <z>10</z>
    </position>
    <position>
      <x>-19.75645</x>
      <y>5.78808451</y>
      <z>10</z>
    </position>
    <position>
      <x>-19.0064526</x>
      <y>5.78808451</y>
      <z>10</z>
    </position>
    <position>
      <x>-18.2564545</x>
      <y>5.66808462</y>
      <z>10</z>
    </position>
    <position>
      <x>-17.5064564</x>
      <y>5.068085</y>
      <z>10</z>
    </position>
    <position>
      <x>-17.3564568</x>
      <y>7.26808548</y>
      <z>10</z>
    </position>
    <position>
      <x>-17.3564568</x>
      <y>8.968085</y>
      <z>10</z>
    </position>
    <position>
      <x>-16.6064587</x>
      <y>10.1680851</y>
      <z>10</z>
    </position>
    <position>
      <x>-15.8564606</x>
      <y>10.8680859</y>
      <z>10</z>
    </position>
    <position>
      <x>-15.1064625</x>
      <y>11.0680847</y>
      <z>10</z>
    </position>
    <position>
      <x>-14.3564644</x>
      <y>10.7680836</y>
      <z>10</z>
    </position>
    <position>
      <x>-14.2064648</x>
      <y>9.968083</y>
      <z>10</z>
    </position>
    <position>
      <x>-14.2064648</x>
      <y>8.668083</y>
      <z>10</z>
    </position>
    <position>
      <x>-13.4564667</x>
      <y>6.868083</y>
      <z>10</z>
    </position>
    <position>
      <x>-12.7064686</x>
      <y>5.510219</y>
      <z>10</z>
    </position>
    <position>
      <x>-12.556469</x>
      <y>7.71021938</y>
      <z>10</z>
    </position>
    <position>
      <x>-12.556469</x>
      <y>9.410219</y>
      <z>10</z>
    </position>
    <position>
      <x>-11.8064709</x>
      <y>10.610219</y>
      <z>10</z>
    </position>
    <position>
      <x>-11.0564728</x>
      <y>11.3102188</y>
      <z>10</z>
    </position>
    <position>
      <x>-10.3064747</x>
      <y>11.5102177</y>
      <z>10</z>
    </position>
    <position>
      <x>-9.556477</x>
      <y>11.2102165</y>
      <z>10</z>
    </position>
    <position>
      <x>-8.8064785</x>
      <y>10.4102163</y>
      <z>10</z>
    </position>
    <position>
      <x>-8.05648</x>
      <y>9.110216</y>
      <z>10</z>
    </position>
    <position>
      <x>-7.30648</x>
      <y>7.31021643</y>
      <z>10</z>
    </position>
    <position>
      <x>-6.55647945</x>
      <y>5.010216</y>
      <z>10</z>
    </position>
    <position>
      <x>-6.40647936</x>
      <y>7.21021652</y>
      <z>10</z>
    </position>
    <position>
      <x>-6.40647936</x>
      <y>8.910216</y>
      <z>10</z>
    </position>
    <position>
      <x>-5.656479</x>
      <y>10.1102161</y>
      <z>10</z>
    </position>
    <position>
      <x>-4.9064784</x>
      <y>10.8102169</y>
      <z>10</z>
    </position>
    <position>
      <x>-4.156478</x>
      <y>11.0102158</y>
      <z>10</z>
    </position>
    <position>
      <x>-3.40647745</x>
      <y>10.7102146</y>
      <z>10</z>
    </position>
    <position>
      <x>-2.656477</x>
      <y>9.910214</y>
      <z>10</z>
    </position>
    <position>
      <x>-1.90647662</x>
      <y>8.610214</y>
      <z>10</z>
    </position>
    <position>
      <x>-1.15647674</x>
      <y>6.810214</y>
      <z>10</z>
    </position>
    <position>
      <x>-0.406476825</x>
      <y>4.610206</y>
      <z>10</z>
    </position>
    <position>
      <x>-0.25647682</x>
      <y>6.81020641</y>
      <z>10</z>
    </position>
    <position>
      <x>-0.25647682</x>
      <y>8.510206</y>
      <z>10</z>
    </position>
    <position>
      <x>0.4935232</x>
      <y>9.710206</y>
      <z>10</z>
    </position>
    <position>
      <x>1.24352312</x>
      <y>10.4102058</y>
      <z>10</z>
    </position>
    <position>
      <x>1.3935231</x>
      <y>12.6102047</y>
      <z>10</z>
    </position>
    <position>
      <x>1.3935231</x>
      <y>14.3102045</y>
      <z>10</z>
    </position>
    <position>
      <x>2.143523</x>
      <y>15.5102043</y>
      <z>10</z>
    </position>
    <position>
      <x>2.89352345</x>
      <y>16.2102051</y>
      <z>10</z>
    </position>
    <position>
      <x>3.643524</x>
      <y>16.4102039</y>
      <z>10</z>
    </position>
    <position>
      <x>4.393524</x>
      <y>16.1102028</y>
      <z>10</z>
    </position>
    <position>
      <x>5.14352465</x>
      <y>15.3102026</y>
      <z>10</z>
    </position>
    <position>
      <x>5.893525</x>
      <y>14.2311859</y>
      <z>10</z>
    </position>
    <position>
      <x>5.743525</x>
      <y>16.4311848</y>
      <z>10</z>
    </position>
    <position>
      <x>5.743525</x>
      <y>18.1311836</y>
      <z>10</z>
    </position>
    <position>
      <x>4.99352455</x>
      <y>19.3311844</y>
      <z>10</z>
    </position>
    <position>
      <x>4.243524</x>
      <y>20.0311852</y>
      <z>10</z>
    </position>
    <position>
      <x>4.393524</x>
      <y>22.231184</y>
      <z>10</z>
    </position>
    <position>
      <x>4.393524</x>
      <y>23.9311829</y>
      <z>10</z>
    </position>
    <position>
      <x>5.14352465</x>
      <y>25.1311836</y>
      <z>10</z>
    </position>
    <position>
      <x>5.893525</x>
      <y>25.8311844</y>
      <z>10</z>
    </position>
    <position>
      <x>6.6435256</x>
      <y>26.0311832</y>
      <z>10</z>
    </position>
    <position>
      <x>7.393526</x>
      <y>25.7311821</y>
      <z>10</z>
    </position>
  </Positions>
  <numFrames>535</numFrames>
  <keyPresses>63</keyPresses>
  <startLoc>
    <x>-39.4064941</x>
    <y>0.8099128</y>
    <z>10</z>
  </startLoc>
</Pos>