<?xml version="1.0" encoding="us-ascii"?>
<Pos xmlns:xsi="http://www.w3.org/2001/XMLSchema-instance" xmlns:xsd="http://www.w3.org/2001/XMLSchema">
  <Positions>
    <position>
      <x>-39.4064941</x>
      <y>0.8099128</y>
      <z>10</z>
    </position>
    <position>
      <x>-40.1565</x>
      <y>0.3199524</y>
      <z>10</z>
    </position>
    <position>
      <x>-40.75201</x>
      <y>0.3199524</y>
      <z>10</z>
    </position>
    <position>
      <x>-40.0020027</x>
      <y>0.3199524</y>
      <z>10</z>
    </position>
    <position>
      <x>-39.2519951</x>
      <y>0.3199524</y>
      <z>10</z>
    </position>
    <position>
      <x>-38.5019875</x>
      <y>0.3199524</y>
      <z>10</z>
    </position>
    <position>
      <x>-37.75198</x>
      <y>0.3199524</y>
      <z>10</z>
    </position>
    <position>
      <x>-37.0019722</x>
      <y>0.3199524</y>
      <z>10</z>
    </position>
    <position>
      <x>-36.2519646</x>
      <y>0.3199524</y>
      <z>10</z>
    </position>
    <position>
      <x>-36.101963</x>
      <y>2.519952</y>
      <z>10</z>
    </position>
    <position>
      <x>-36.101963</x>
      <y>4.21995163</y>
      <z>10</z>
    </position>
    <position>
      <x>-35.95196</x>
      <y>6.419952</y>
      <z>10</z>
    </position>
    <position>
      <x>-35.95196</x>
      <y>8.119952</y>
      <z>10</z>
    </position>
    <position>
      <x>-36.70197</x>
      <y>9.319952</y>
      <z>10</z>
    </position>
    <position>
      <x>-37.4519768</x>
      <y>10.0199528</y>
      <z>10</z>
    </position>
    <position>
      <x>-38.2019844</x>
      <y>10.2199516</y>
      <z>10</z>
    </position>
    <position>
      <x>-38.951992</x>
      <y>9.91995049</y>
      <z>10</z>
    </position>
    <position>
      <x>-39.702</x>
      <y>9.11995</y>
      <z>10</z>
    </position>
    <position>
      <x>-40.4520073</x>
      <y>7.91756248</y>
      <z>10</z>
    </position>
    <position>
      <x>-40.60201</x>
      <y>10.1175613</y>
      <z>10</z>
    </position>
    <position>
      <x>-40.60201</x>
      <y>11.8175611</y>
      <z>10</z>
    </position>
    <position>
      <x>-39.852</x>
      <y>13.017561</y>
      <z>10</z>
    </position>
    <position>
      <x>-39.1019936</x>
      <y>13.7175617</y>
      <z>10</z>
    </position>
    <position>
      <x>-38.3519859</x>
      <y>13.9175606</y>
      <z>10</z>
    </position>
    <position>
      <x>-37.60198</x>
      <y>13.6175594</y>
      <z>10</z>
    </position>
    <position>
      <x>-37.4519768</x>
      <y>15.8175583</y>
      <z>10</z>
    </position>
    <position>
      <x>-37.4519768</x>
      <y>17.5175571</y>
      <z>10</z>
    </position>
    <position>
      <x>-36.70197</x>
      <y>18.7175579</y>
      <z>10</z>
    </position>
    <position>
      <x>-35.95196</x>
      <y>19.4175587</y>
      <z>10</z>
    </position>
    <position>
      <x>-35.2019539</x>
      <y>19.6175575</y>
      <z>10</z>
    </position>
    <position>
      <x>-34.4519463</x>
      <y>19.3175564</y>
      <z>10</z>
    </position>
    <position>
      <x>-33.70194</x>
      <y>18.5175552</y>
      <z>10</z>
    </position>
    <position>
      <x>-32.95193</x>
      <y>17.217556</y>
      <z>10</z>
    </position>
    <position>
      <x>-32.2019234</x>
      <y>16.1135921</y>
      <z>10</z>
    </position>
    <position>
      <x>-31.4519234</x>
      <y>16.1135921</y>
      <z>10</z>
    </position>
    <position>
      <x>-31.3019238</x>
      <y>18.313591</y>
      <z>10</z>
    </position>
    <position>
      <x>-31.3019238</x>
      <y>20.01359</y>
      <z>10</z>
    </position>
    <position>
      <x>-32.05192</x>
      <y>21.21359</y>
      <z>10</z>
    </position>
    <position>
      <x>-32.80193</x>
      <y>21.9135914</y>
      <z>10</z>
    </position>
    <position>
      <x>-32.95193</x>
      <y>24.11359</y>
      <z>10</z>
    </position>
    <position>
      <x>-32.95193</x>
      <y>25.81359</y>
      <z>10</z>
    </position>
    <position>
      <x>-32.2019234</x>
      <y>27.01359</y>
      <z>10</z>
    </position>
    <position>
      <x>-31.4519234</x>
      <y>27.71359</y>
      <z>10</z>
    </position>
    <position>
      <x>-30.7019253</x>
      <y>27.91359</y>
      <z>10</z>
    </position>
    <position>
      <x>-29.9519272</x>
      <y>27.6135883</y>
      <z>10</z>
    </position>
    <position>
      <x>-29.20193</x>
      <y>26.8135872</y>
      <z>10</z>
    </position>
    <position>
      <x>-28.451931</x>
      <y>25.513588</y>
      <z>10</z>
    </position>
    <position>
      <x>-27.7019329</x>
      <y>23.640871</y>
      <z>10</z>
    </position>
    <position>
      <x>-26.9519348</x>
      <y>23.640871</y>
      <z>10</z>
    </position>
    <position>
      <x>-26.2019367</x>
      <y>23.640871</y>
      <z>10</z>
    </position>
    <position>
      <x>-25.4519386</x>
      <y>23.640871</y>
      <z>10</z>
    </position>
    <position>
      <x>-24.70194</x>
      <y>23.34087</y>
      <z>10</z>
    </position>
    <position>
      <x>-23.9519424</x>
      <y>22.5408688</y>
      <z>10</z>
    </position>
    <position>
      <x>-23.2019444</x>
      <y>21.24087</y>
      <z>10</z>
    </position>
    <position>
      <x>-22.4519463</x>
      <y>19.44087</y>
      <z>10</z>
    </position>
    <position>
      <x>-22.3019466</x>
      <y>21.64087</y>
      <z>10</z>
    </position>
    <position>
      <x>-22.3019466</x>
      <y>23.340868</y>
      <z>10</z>
    </position>
    <position>
      <x>-21.5519485</x>
      <y>24.1299648</y>
      <z>10</z>
    </position>
    <position>
      <x>-20.80195</x>
      <y>23.7299633</y>
      <z>10</z>
    </position>
    <position>
      <x>-20.0519524</x>
      <y>22.8299637</y>
      <z>10</z>
    </position>
    <position>
      <x>-19.3019543</x>
      <y>21.4299641</y>
      <z>10</z>
    </position>
    <position>
      <x>-18.5519562</x>
      <y>19.5299644</y>
      <z>10</z>
    </position>
    <position>
      <x>-17.8019581</x>
      <y>17.1299629</y>
      <z>10</z>
    </position>
    <position>
      <x>-17.05196</x>
      <y>14.2299623</y>
      <z>10</z>
    </position>
    <position>
      <x>-16.3019619</x>
      <y>10.8299618</y>
      <z>10</z>
    </position>
    <position>
      <x>-15.5519638</x>
      <y>6.92996264</y>
      <z>10</z>
    </position>
    <position>
      <x>-14.8019657</x>
      <y>5.510219</y>
      <z>10</z>
    </position>
    <position>
      <x>-14.6519661</x>
      <y>7.71021938</y>
      <z>10</z>
    </position>
    <position>
      <x>-14.6519661</x>
      <y>9.410219</y>
      <z>10</z>
    </position>
    <position>
      <x>-13.901968</x>
      <y>10.610219</y>
      <z>10</z>
    </position>
    <position>
      <x>-13.15197</x>
      <y>11.3102188</y>
      <z>10</z>
    </position>
    <position>
      <x>-12.4019718</x>
      <y>11.5102177</y>
      <z>10</z>
    </position>
    <position>
      <x>-11.6519737</x>
      <y>11.2102165</y>
      <z>10</z>
    </position>
    <position>
      <x>-10.9019756</x>
      <y>10.4102163</y>
      <z>10</z>
    </position>
    <position>
      <x>-10.1519775</x>
      <y>9.110216</y>
      <z>10</z>
    </position>
    <position>
      <x>-10.3019772</x>
      <y>11.310215</y>
      <z>10</z>
    </position>
    <position>
      <x>-10.3019772</x>
      <y>13.0102148</y>
      <z>10</z>
    </position>
    <position>
      <x>-9.551979</x>
      <y>14.2102146</y>
      <z>10</z>
    </position>
    <position>
      <x>-8.801981</x>
      <y>14.9102154</y>
      <z>10</z>
    </position>
    <position>
      <x>-8.651981</x>
      <y>15.1102142</y>
      <z>10</z>
    </position>
    <position>
      <x>-8.651981</x>
      <y>14.8102131</y>
      <z>10</z>
    </position>
    <position>
      <x>-7.901983</x>
      <y>14.0102129</y>
      <z>10</z>
    </position>
    <position>
      <x>-7.15198231</x>
      <y>12.7102127</y>
      <z>10</z>
    </position>
    <position>
      <x>-7.001982</x>
      <y>10.9102125</y>
      <z>10</z>
    </position>
    <position>
      <x>-7.001982</x>
      <y>8.610211</y>
      <z>10</z>
    </position>
    <position>
      <x>-6.25198174</x>
      <y>5.810211</y>
      <z>10</z>
    </position>
    <position>
      <x>-5.50198126</x>
      <y>3.39641619</y>
      <z>10</z>
    </position>
    <position>
      <x>-5.351981</x>
      <y>5.59641647</y>
      <z>10</z>
    </position>
    <position>
      <x>-5.351981</x>
      <y>7.296416</y>
      <z>10</z>
    </position>
    <position>
      <x>-4.60198069</x>
      <y>8.496415</y>
      <z>10</z>
    </position>
    <position>
      <x>-3.85198021</x>
      <y>9.196415</y>
      <z>10</z>
    </position>
    <position>
      <x>-3.10197973</x>
      <y>9.396414</y>
      <z>10</z>
    </position>
    <position>
      <x>-2.35197926</x>
      <y>9.096413</y>
      <z>10</z>
    </position>
    <position>
      <x>-2.20197916</x>
      <y>11.2964115</y>
      <z>10</z>
    </position>
    <position>
      <x>-2.20197916</x>
      <y>12.9964113</y>
      <z>10</z>
    </position>
    <position>
      <x>-1.45197916</x>
      <y>14.1964111</y>
      <z>10</z>
    </position>
    <position>
      <x>-0.7019793</x>
      <y>14.8964119</y>
      <z>10</z>
    </position>
    <position>
      <x>0.04802072</x>
      <y>15.0964108</y>
      <z>10</z>
    </position>
    <position>
      <x>0.7980207</x>
      <y>15.1311855</y>
      <z>10</z>
    </position>
    <position>
      <x>0.9480207</x>
      <y>17.3311844</y>
      <z>10</z>
    </position>
    <position>
      <x>0.9480207</x>
      <y>19.0311832</y>
      <z>10</z>
    </position>
    <position>
      <x>1.69802058</x>
      <y>20.231184</y>
      <z>10</z>
    </position>
    <position>
      <x>2.4480207</x>
      <y>20.9311848</y>
      <z>10</z>
    </position>
    <position>
      <x>2.59802079</x>
      <y>23.1311836</y>
      <z>10</z>
    </position>
    <position>
      <x>2.59802079</x>
      <y>24.8311825</y>
      <z>10</z>
    </position>
    <position>
      <x>3.34802127</x>
      <y>26.0311832</y>
      <z>10</z>
    </position>
    <position>
      <x>4.09802151</x>
      <y>26.731184</y>
      <z>10</z>
    </position>
    <position>
      <x>4.848022</x>
      <y>26.9311829</y>
      <z>10</z>
    </position>
    <position>
      <x>5.59802246</x>
      <y>26.6311817</y>
      <z>10</z>
    </position>
    <position>
      <x>6.348023</x>
      <y>25.83118</y>
      <z>10</z>
    </position>
  </Positions>
  <numFrames>550</numFrames>
  <keyPresses>48</keyPresses>
  <startLoc>
    <x>-39.4064941</x>
    <y>0.8099128</y>
    <z>10</z>
  </startLoc>
</Pos>