<?xml version="1.0" encoding="us-ascii"?>
<Pos xmlns:xsi="http://www.w3.org/2001/XMLSchema-instance" xmlns:xsd="http://www.w3.org/2001/XMLSchema">
  <Positions>
    <position>
      <x>-39.4064941</x>
      <y>0.8099128</y>
      <z>10</z>
    </position>
    <position>
      <x>-40.1565</x>
      <y>0.3199524</y>
      <z>10</z>
    </position>
    <position>
      <x>-40.75201</x>
      <y>0.3199524</y>
      <z>10</z>
    </position>
    <position>
      <x>-40.7295227</x>
      <y>0.3199524</y>
      <z>10</z>
    </position>
    <position>
      <x>-40.7070351</x>
      <y>0.3199524</y>
      <z>10</z>
    </position>
    <position>
      <x>-39.9570274</x>
      <y>0.3199524</y>
      <z>10</z>
    </position>
    <position>
      <x>-39.20702</x>
      <y>0.3199524</y>
      <z>10</z>
    </position>
    <position>
      <x>-38.4570122</x>
      <y>0.3199524</y>
      <z>10</z>
    </position>
    <position>
      <x>-37.7070045</x>
      <y>0.3199524</y>
      <z>10</z>
    </position>
    <position>
      <x>-36.9569969</x>
      <y>0.3199524</y>
      <z>10</z>
    </position>
    <position>
      <x>-36.20699</x>
      <y>0.3199524</y>
      <z>10</z>
    </position>
    <position>
      <x>-36.35699</x>
      <y>2.519952</y>
      <z>10</z>
    </position>
    <position>
      <x>-36.35699</x>
      <y>4.21995163</y>
      <z>10</z>
    </position>
    <position>
      <x>-36.5069923</x>
      <y>6.419952</y>
      <z>10</z>
    </position>
    <position>
      <x>-36.5069923</x>
      <y>8.119952</y>
      <z>10</z>
    </position>
    <position>
      <x>-37.257</x>
      <y>9.319952</y>
      <z>10</z>
    </position>
    <position>
      <x>-38.0070076</x>
      <y>10.0199528</y>
      <z>10</z>
    </position>
    <position>
      <x>-38.7570152</x>
      <y>10.2199516</y>
      <z>10</z>
    </position>
    <position>
      <x>-39.5070229</x>
      <y>9.91995049</y>
      <z>10</z>
    </position>
    <position>
      <x>-40.25703</x>
      <y>9.11995</y>
      <z>10</z>
    </position>
    <position>
      <x>-40.69804</x>
      <y>7.91756248</y>
      <z>10</z>
    </position>
    <position>
      <x>-40.69804</x>
      <y>10.1175613</y>
      <z>10</z>
    </position>
    <position>
      <x>-40.69804</x>
      <y>11.8175611</y>
      <z>10</z>
    </position>
    <position>
      <x>-39.9480324</x>
      <y>13.017561</y>
      <z>10</z>
    </position>
    <position>
      <x>-39.1980247</x>
      <y>13.7175617</y>
      <z>10</z>
    </position>
    <position>
      <x>-38.4480171</x>
      <y>13.9175606</y>
      <z>10</z>
    </position>
    <position>
      <x>-37.69801</x>
      <y>13.6175594</y>
      <z>10</z>
    </position>
    <position>
      <x>-37.548008</x>
      <y>15.8175583</y>
      <z>10</z>
    </position>
    <position>
      <x>-37.548008</x>
      <y>17.5175571</y>
      <z>10</z>
    </position>
    <position>
      <x>-36.798</x>
      <y>18.7175579</y>
      <z>10</z>
    </position>
    <position>
      <x>-36.0479927</x>
      <y>19.4175587</y>
      <z>10</z>
    </position>
    <position>
      <x>-35.2979851</x>
      <y>19.6175575</y>
      <z>10</z>
    </position>
    <position>
      <x>-34.5479774</x>
      <y>19.3175564</y>
      <z>10</z>
    </position>
    <position>
      <x>-33.79797</x>
      <y>18.5175552</y>
      <z>10</z>
    </position>
    <position>
      <x>-33.0479622</x>
      <y>17.217556</y>
      <z>10</z>
    </position>
    <position>
      <x>-32.2979546</x>
      <y>16.1135921</y>
      <z>10</z>
    </position>
    <position>
      <x>-31.5479546</x>
      <y>16.1135921</y>
      <z>10</z>
    </position>
    <position>
      <x>-31.3979549</x>
      <y>18.313591</y>
      <z>10</z>
    </position>
    <position>
      <x>-31.3979549</x>
      <y>20.01359</y>
      <z>10</z>
    </position>
    <position>
      <x>-30.6479568</x>
      <y>21.21359</y>
      <z>10</z>
    </position>
    <position>
      <x>-29.8979588</x>
      <y>21.58087</y>
      <z>10</z>
    </position>
    <position>
      <x>-29.14796</x>
      <y>21.08087</y>
      <z>10</z>
    </position>
    <position>
      <x>-28.3979626</x>
      <y>20.08087</y>
      <z>10</z>
    </position>
    <position>
      <x>-27.6479645</x>
      <y>18.58087</y>
      <z>10</z>
    </position>
    <position>
      <x>-26.8979664</x>
      <y>16.58087</y>
      <z>10</z>
    </position>
    <position>
      <x>-26.1479683</x>
      <y>14.0808678</y>
      <z>10</z>
    </position>
    <position>
      <x>-25.39797</x>
      <y>11.0808668</y>
      <z>10</z>
    </position>
    <position>
      <x>-24.6479721</x>
      <y>7.580867</y>
      <z>10</z>
    </position>
    <position>
      <x>-23.897974</x>
      <y>3.58086824</y>
      <z>10</z>
    </position>
    <position>
      <x>-23.7479744</x>
      <y>5.78086853</y>
      <z>10</z>
    </position>
    <position>
      <x>-23.7479744</x>
      <y>7.480868</y>
      <z>10</z>
    </position>
    <position>
      <x>-22.9979763</x>
      <y>8.680867</y>
      <z>10</z>
    </position>
    <position>
      <x>-22.2479782</x>
      <y>9.380867</y>
      <z>10</z>
    </position>
    <position>
      <x>-21.49798</x>
      <y>9.580866</y>
      <z>10</z>
    </position>
    <position>
      <x>-20.747982</x>
      <y>9.280865</y>
      <z>10</z>
    </position>
    <position>
      <x>-20.5979824</x>
      <y>8.480865</y>
      <z>10</z>
    </position>
    <position>
      <x>-20.5979824</x>
      <y>7.180864</y>
      <z>10</z>
    </position>
    <position>
      <x>-19.8479843</x>
      <y>5.78808451</y>
      <z>10</z>
    </position>
    <position>
      <x>-19.0979862</x>
      <y>5.78808451</y>
      <z>10</z>
    </position>
    <position>
      <x>-18.9479866</x>
      <y>7.988085</y>
      <z>10</z>
    </position>
    <position>
      <x>-18.9479866</x>
      <y>9.688085</y>
      <z>10</z>
    </position>
    <position>
      <x>-18.1979885</x>
      <y>10.8880844</y>
      <z>10</z>
    </position>
    <position>
      <x>-17.44799</x>
      <y>11.5880852</y>
      <z>10</z>
    </position>
    <position>
      <x>-16.6979923</x>
      <y>11.788084</y>
      <z>10</z>
    </position>
    <position>
      <x>-15.9479942</x>
      <y>11.4880829</y>
      <z>10</z>
    </position>
    <position>
      <x>-15.1979961</x>
      <y>10.6880827</y>
      <z>10</z>
    </position>
    <position>
      <x>-14.447998</x>
      <y>9.3880825</y>
      <z>10</z>
    </position>
    <position>
      <x>-13.698</x>
      <y>7.588083</y>
      <z>10</z>
    </position>
    <position>
      <x>-12.9480019</x>
      <y>5.510219</y>
      <z>10</z>
    </position>
    <position>
      <x>-13.0980015</x>
      <y>7.71021938</y>
      <z>10</z>
    </position>
    <position>
      <x>-13.0980015</x>
      <y>9.410219</y>
      <z>10</z>
    </position>
    <position>
      <x>-12.3480034</x>
      <y>10.610219</y>
      <z>10</z>
    </position>
    <position>
      <x>-11.5980053</x>
      <y>11.3102188</y>
      <z>10</z>
    </position>
    <position>
      <x>-10.8480072</x>
      <y>11.5102177</y>
      <z>10</z>
    </position>
    <position>
      <x>-10.0980091</x>
      <y>11.2102165</y>
      <z>10</z>
    </position>
    <position>
      <x>-9.348011</x>
      <y>10.4102163</y>
      <z>10</z>
    </position>
    <position>
      <x>-8.598013</x>
      <y>9.110216</y>
      <z>10</z>
    </position>
    <position>
      <x>-7.848014</x>
      <y>7.31021643</y>
      <z>10</z>
    </position>
    <position>
      <x>-7.0980134</x>
      <y>5.010216</y>
      <z>10</z>
    </position>
    <position>
      <x>-6.94801331</x>
      <y>7.21021652</y>
      <z>10</z>
    </position>
    <position>
      <x>-6.94801331</x>
      <y>8.910216</y>
      <z>10</z>
    </position>
    <position>
      <x>-6.198013</x>
      <y>10.1102161</y>
      <z>10</z>
    </position>
    <position>
      <x>-5.44801235</x>
      <y>10.8102169</y>
      <z>10</z>
    </position>
    <position>
      <x>-4.698012</x>
      <y>11.0102158</y>
      <z>10</z>
    </position>
    <position>
      <x>-3.9480114</x>
      <y>10.7102146</y>
      <z>10</z>
    </position>
    <position>
      <x>-3.198011</x>
      <y>9.910214</y>
      <z>10</z>
    </position>
    <position>
      <x>-2.44801044</x>
      <y>8.610214</y>
      <z>10</z>
    </position>
    <position>
      <x>-1.69801033</x>
      <y>6.810214</y>
      <z>10</z>
    </position>
    <position>
      <x>-0.948010445</x>
      <y>4.610206</y>
      <z>10</z>
    </position>
    <position>
      <x>-0.798010468</x>
      <y>6.81020641</y>
      <z>10</z>
    </position>
    <position>
      <x>-0.798010468</x>
      <y>8.510206</y>
      <z>10</z>
    </position>
    <position>
      <x>-0.798010468</x>
      <y>10.7102051</y>
      <z>10</z>
    </position>
    <position>
      <x>-0.798010468</x>
      <y>12.4102049</y>
      <z>10</z>
    </position>
    <position>
      <x>-0.04801047</x>
      <y>13.6102047</y>
      <z>10</z>
    </position>
    <position>
      <x>0.701989532</x>
      <y>14.3102055</y>
      <z>10</z>
    </position>
    <position>
      <x>0.8519895</x>
      <y>14.5102043</y>
      <z>10</z>
    </position>
    <position>
      <x>0.8519895</x>
      <y>14.2311859</y>
      <z>10</z>
    </position>
    <position>
      <x>0.701989532</x>
      <y>16.4311848</y>
      <z>10</z>
    </position>
    <position>
      <x>0.701989532</x>
      <y>18.1311836</y>
      <z>10</z>
    </position>
    <position>
      <x>1.45198941</x>
      <y>19.3311844</y>
      <z>10</z>
    </position>
    <position>
      <x>2.20198941</x>
      <y>20.0311852</y>
      <z>10</z>
    </position>
    <position>
      <x>2.35198951</x>
      <y>22.231184</y>
      <z>10</z>
    </position>
    <position>
      <x>2.35198951</x>
      <y>23.9311829</y>
      <z>10</z>
    </position>
    <position>
      <x>3.10199</x>
      <y>25.1311836</y>
      <z>10</z>
    </position>
    <position>
      <x>3.85199046</x>
      <y>25.8311844</y>
      <z>10</z>
    </position>
    <position>
      <x>4.6019907</x>
      <y>26.0311832</y>
      <z>10</z>
    </position>
    <position>
      <x>5.351991</x>
      <y>25.7311821</y>
      <z>10</z>
    </position>
    <position>
      <x>6.10199165</x>
      <y>24.931181</y>
      <z>10</z>
    </position>
  </Positions>
  <numFrames>540</numFrames>
  <keyPresses>49</keyPresses>
  <startLoc>
    <x>-39.4064941</x>
    <y>0.8099128</y>
    <z>10</z>
  </startLoc>
</Pos>